{
  "gitSyncId": "66959955819ac61979db6c71_672dd8b0-037c-43f6-a858-c2efec3b8822",
  "id": "Clients_clients.closeClientModal",
  "pluginId": "js-plugin",
  "pluginType": "JS",
  "unpublishedAction": {
    "actionConfiguration": {
      "encodeParamsToggle": true,
      "jsArguments": [],
      "paginationType": "NONE",
      "timeoutInMillisecond": 10000
    },
    "collectionId": "Clients_clients",
    "confirmBeforeExecute": false,
    "datasource": {
      "isAutoGenerated": false,
      "name": "UNUSED_DATASOURCE",
      "pluginId": "js-plugin"
    },
    "dynamicBindingPathList": [
      {
        "key": "body"
      }
    ],
    "fullyQualifiedName": "clients.closeClientModal",
    "name": "closeClientModal",
    "pageId": "Clients",
    "runBehaviour": "MANUAL",
    "userSetOnLoad": false
  }
}