{
  "gitSyncId": "691b2aa4dd6b1b7f5b14dd39_2945d348-660e-4cce-821e-a1ad8c90b3b6",
  "id": "Accounts_hrPositions.openPositionModal",
  "pluginId": "js-plugin",
  "pluginType": "JS",
  "unpublishedAction": {
    "actionConfiguration": {
      "encodeParamsToggle": true,
      "jsArguments": [
        {
          "name": "mode",
          "value": "add"
        },
        {
          "name": "row",
          "value": "{{null}}"
        }
      ],
      "paginationType": "NONE",
      "timeoutInMillisecond": 10000
    },
    "collectionId": "Accounts_hrPositions",
    "confirmBeforeExecute": false,
    "datasource": {
      "isAutoGenerated": false,
      "name": "UNUSED_DATASOURCE",
      "pluginId": "js-plugin"
    },
    "dynamicBindingPathList": [
      {
        "key": "body"
      }
    ],
    "fullyQualifiedName": "hrPositions.openPositionModal",
    "name": "openPositionModal",
    "pageId": "Accounts",
    "runBehaviour": "MANUAL",
    "userSetOnLoad": false
  }
}