{
  "gitSyncId": "691b2aa4dd6b1b7f5b14dd39_d63d56f1-5b96-4e99-a67f-cead10c26d7f",
  "id": "Salary_utils.getAccrualTypesRaw",
  "pluginId": "js-plugin",
  "pluginType": "JS",
  "unpublishedAction": {
    "actionConfiguration": {
      "encodeParamsToggle": true,
      "jsArguments": [],
      "paginationType": "NONE",
      "timeoutInMillisecond": 10000
    },
    "collectionId": "Salary_utils",
    "confirmBeforeExecute": false,
    "datasource": {
      "isAutoGenerated": false,
      "name": "UNUSED_DATASOURCE",
      "pluginId": "js-plugin"
    },
    "dynamicBindingPathList": [
      {
        "key": "body"
      }
    ],
    "fullyQualifiedName": "utils.getAccrualTypesRaw",
    "name": "getAccrualTypesRaw",
    "pageId": "Salary",
    "runBehaviour": "MANUAL",
    "userSetOnLoad": false
  }
}