{
  "animateLoading": true,
  "borderRadius": "{{appsmith.theme.borderRadius.appBorderRadius}}",
  "bottomRow": 35,
  "boxShadow": "none",
  "buttonColor": "{{appsmith.theme.colors.primaryColor}}",
  "buttonStyle": "PRIMARY_BUTTON",
  "buttonVariant": "PRIMARY",
  "disabledWhenInvalid": false,
  "dynamicBindingPathList": [
    {
      "key": "buttonColor"
    },
    {
      "key": "borderRadius"
    }
  ],
  "dynamicTriggerPathList": [],
  "isDefaultClickDisabled": true,
  "isDisabled": false,
  "isLoading": false,
  "isVisible": true,
  "key": "envon1alty",
  "leftColumn": 47,
  "minWidth": 120,
  "mobileBottomRow": 22,
  "mobileLeftColumn": 47,
  "mobileRightColumn": 63,
  "mobileTopRow": 18,
  "needsErrorInfo": false,
  "parentId": "bsayexur5m",
  "placement": "CENTER",
  "recaptchaType": "V3",
  "renderMode": "CANVAS",
  "resetFormOnClick": false,
  "responsiveBehavior": "hug",
  "rightColumn": 64,
  "text": "Добавить",
  "topRow": 31,
  "type": "BUTTON_WIDGET",
  "version": 1,
  "widgetId": "c7ip4jkjtj",
  "widgetName": "Button2"
}