{
  "gitSyncId": "691b2aa4dd6b1b7f5b14dd39_a8a810dd-4210-4875-bcb2-c071e91e1784",
  "id": "HR_items.refreshAccessToken",
  "pluginId": "js-plugin",
  "pluginType": "JS",
  "unpublishedAction": {
    "actionConfiguration": {
      "encodeParamsToggle": true,
      "jsArguments": [],
      "paginationType": "NONE",
      "timeoutInMillisecond": 10000
    },
    "collectionId": "HR_items",
    "confirmBeforeExecute": false,
    "datasource": {
      "isAutoGenerated": false,
      "name": "UNUSED_DATASOURCE",
      "pluginId": "js-plugin"
    },
    "dynamicBindingPathList": [
      {
        "key": "body"
      }
    ],
    "fullyQualifiedName": "items.refreshAccessToken",
    "name": "refreshAccessToken",
    "pageId": "HR",
    "runBehaviour": "MANUAL",
    "userSetOnLoad": false
  }
}