{
  "gitSyncId": "691b2aa4dd6b1b7f5b14dd39_d86ef87b-abec-4865-8580-45b41578a408",
  "id": "Salary_utils.getAccrualsBySalaryId",
  "pluginId": "js-plugin",
  "pluginType": "JS",
  "unpublishedAction": {
    "actionConfiguration": {
      "encodeParamsToggle": true,
      "jsArguments": [
        {
          "name": "salaryIds",
          "value": "{{[]}}"
        }
      ],
      "paginationType": "NONE",
      "timeoutInMillisecond": 10000
    },
    "collectionId": "Salary_utils",
    "confirmBeforeExecute": false,
    "datasource": {
      "isAutoGenerated": false,
      "name": "UNUSED_DATASOURCE",
      "pluginId": "js-plugin"
    },
    "dynamicBindingPathList": [
      {
        "key": "body"
      }
    ],
    "fullyQualifiedName": "utils.getAccrualsBySalaryId",
    "name": "getAccrualsBySalaryId",
    "pageId": "Salary",
    "runBehaviour": "MANUAL",
    "userSetOnLoad": false
  }
}