{
  "gitSyncId": "691b2aa4dd6b1b7f5b14dd39_1b864db5-364c-4760-aa0a-4cbea4357f66",
  "id": "HR_nav.menuItems",
  "pluginId": "js-plugin",
  "pluginType": "JS",
  "unpublishedAction": {
    "actionConfiguration": {
      "encodeParamsToggle": true,
      "jsArguments": [
        {
          "name": "currentPageCode",
          "value": ""
        }
      ],
      "paginationType": "NONE",
      "timeoutInMillisecond": 10000
    },
    "collectionId": "HR_nav",
    "confirmBeforeExecute": false,
    "datasource": {
      "isAutoGenerated": false,
      "name": "UNUSED_DATASOURCE",
      "pluginId": "js-plugin"
    },
    "dynamicBindingPathList": [
      {
        "key": "body"
      }
    ],
    "fullyQualifiedName": "nav.menuItems",
    "name": "menuItems",
    "pageId": "HR",
    "runBehaviour": "MANUAL",
    "userSetOnLoad": false
  }
}