{
  "gitSyncId": "691b2aa4dd6b1b7f5b14dd39_1484b0d2-6308-4be9-92ec-e1ac7f5e83f8",
  "id": "HR_hrDictionaries.tbl_position_titles_onRowSelected",
  "pluginId": "js-plugin",
  "pluginType": "JS",
  "unpublishedAction": {
    "actionConfiguration": {
      "encodeParamsToggle": true,
      "jsArguments": [
        {
          "name": "rowParam",
          "value": "{{null}}"
        }
      ],
      "paginationType": "NONE",
      "timeoutInMillisecond": 10000
    },
    "collectionId": "HR_hrDictionaries",
    "confirmBeforeExecute": false,
    "datasource": {
      "isAutoGenerated": false,
      "name": "UNUSED_DATASOURCE",
      "pluginId": "js-plugin"
    },
    "dynamicBindingPathList": [
      {
        "key": "body"
      }
    ],
    "fullyQualifiedName": "hrDictionaries.tbl_position_titles_onRowSelected",
    "name": "tbl_position_titles_onRowSelected",
    "pageId": "HR",
    "runBehaviour": "MANUAL",
    "userSetOnLoad": false
  }
}