{
  "accentColor": "{{appsmith.theme.colors.primaryColor}}",
  "animateLoading": true,
  "autoFocus": false,
  "borderRadius": "{{appsmith.theme.borderRadius.appBorderRadius}}",
  "bottomRow": 24,
  "boxShadow": "none",
  "defaultText": "",
  "displayName": "Input",
  "dynamicBindingPathList": [
    {
      "key": "accentColor"
    },
    {
      "key": "borderRadius"
    }
  ],
  "dynamicHeight": "FIXED",
  "dynamicTriggerPathList": [],
  "hideCard": false,
  "iconAlign": "left",
  "iconSVG": "/static/media/icon.9f505595da61a34f563dba82adeb06ec.svg",
  "inputType": "EMAIL",
  "isDeprecated": false,
  "isDisabled": false,
  "isLoading": false,
  "isRequired": true,
  "isVisible": true,
  "key": "2use2p5sva",
  "label": "Email",
  "labelAlignment": "left",
  "labelPosition": "Top",
  "labelStyle": "",
  "labelTextSize": "0.875rem",
  "labelWidth": 5,
  "leftColumn": 4,
  "maxDynamicHeight": 9000,
  "minDynamicHeight": 4,
  "originalBottomRow": 24,
  "originalTopRow": 16,
  "parentColumnSpace": 18.1875,
  "parentId": "3zaeh40bua",
  "parentRowSpace": 10,
  "placeholderText": "       Введите email",
  "renderMode": "CANVAS",
  "resetOnSubmit": true,
  "rightColumn": 61,
  "searchTags": [
    "form",
    "text input",
    "number",
    "textarea"
  ],
  "topRow": 16,
  "type": "INPUT_WIDGET_V2",
  "version": 2,
  "widgetId": "nckbq8kovr",
  "widgetName": "inp_email"
}