{
  "gitSyncId": "691b2aa4dd6b1b7f5b14dd39_645a5dc4-62e9-449a-8225-eb398d439b5b",
  "id": "Salary_salary.createRecurringAccrualsFromPreviousMonth",
  "pluginId": "js-plugin",
  "pluginType": "JS",
  "unpublishedAction": {
    "actionConfiguration": {
      "encodeParamsToggle": true,
      "jsArguments": [
        {
          "name": "previousSalaryId"
        },
        {
          "name": "newSalaryId"
        }
      ],
      "paginationType": "NONE",
      "timeoutInMillisecond": 10000
    },
    "collectionId": "Salary_salary",
    "confirmBeforeExecute": false,
    "datasource": {
      "isAutoGenerated": false,
      "name": "UNUSED_DATASOURCE",
      "pluginId": "js-plugin"
    },
    "dynamicBindingPathList": [
      {
        "key": "body"
      }
    ],
    "fullyQualifiedName": "salary.createRecurringAccrualsFromPreviousMonth",
    "name": "createRecurringAccrualsFromPreviousMonth",
    "pageId": "Salary",
    "runBehaviour": "MANUAL",
    "userSetOnLoad": false
  }
}